DevLType
